{
  "project_info": {
    "project_number": "245689421132",
    "project_id": "chapatuchamba-40b8d",
    "storage_bucket": "chapatuchamba-40b8d.appspot.com"
  },
  "client": [
    {
      "client_info": {
        "mobilesdk_app_id": "1:245689421132:android:8c9cf60cc826c629da53e9",
        "android_client_info": {
          "package_name": "com.example.trabajofinal"
        }
      },
      "oauth_client": [
        {
          "client_id": "245689421132-ogmnacu5c5jolbchnbjvo9r15renh5kj.apps.googleusercontent.com",
          "client_type": 3
        }
      ],
      "api_key": [
        {
          "current_key": "AIzaSyAwxty6o11MxjvF3aQ0bnromvr2EDZjl6c"
        }
      ],
      "services": {
        "appinvite_service": {
          "other_platform_oauth_client": [
            {
              "client_id": "245689421132-ogmnacu5c5jolbchnbjvo9r15renh5kj.apps.googleusercontent.com",
              "client_type": 3
            }
          ]
        }
      }
    }
  ],
  "configuration_version": "1"
}